{
    "$schema": "http://json-schema.org/draft-07/schema#",
    "definitions": {
        "Airline": {
            "additionalProperties": false,
            "properties": {
                "airlineId": {
                    "type": "number"
                },
                "airlineName": {
                    "type": "string"
                },
                "country": {
                    "type": "string"
                },
                "destination": {
                    "type": "string"
                },
                "established": {
                    "type": "string"
                },
                "fleetSize": {
                    "type": "number"
                },
                "headQuarters": {
                    "type": "string"
                },
                "international": {
                    "type": "boolean"
                },
                "logo": {
                    "type": "string"
                },
                "popularity": {
                    "type": "number"
                },
                "slogan": {
                    "type": "string"
                },
                "tags": {
                    "items": {
                        "type": "string"
                    },
                    "type": "array"
                },
                "website": {
                    "type": "string"
                }
            },
            "required": [
                "airlineId",
                "airlineName",
                "country",
                "destination",
                "established",
                "fleetSize",
                "headQuarters",
                "international",
                "logo",
                "popularity",
                "slogan",
                "tags",
                "website"
            ],
            "type": "object"
        },
        "AirlineFleetQueryParams": {
            "additionalProperties": false,
            "properties": {
                "airlineId": {
                    "type": "number"
                },
                "airlineName": {
                    "type": "string"
                },
                "destination": {
                    "type": "string"
                }
            },
            "required": [
                "airlineId"
            ],
            "type": "object"
        }
    }
}

